MANIFEST.in
README.txt
setup.py
AIKIF.egg-info/PKG-INFO
AIKIF.egg-info/SOURCES.txt
AIKIF.egg-info/dependency_links.txt
AIKIF.egg-info/requires.txt
AIKIF.egg-info/top_level.txt
aikif/__init__.py
aikif/bias.py
aikif/cls_file_mapping.py
aikif/cls_log.py
aikif/config.py
aikif/core_data.py
aikif/decorators.py
aikif/index.py
aikif/knowledge.py
aikif/mapper.py
aikif/programs.py
aikif/project.py
aikif/agents/__init__.py
aikif/agents/agent.py
aikif/agents/agent_interface_env.py
aikif/agents/agent_map_data.py
aikif/agents/aggregate/__init__.py
aikif/agents/aggregate/load_PC_usage.py
aikif/agents/explore/__init__.py
aikif/agents/explore/agent_explore_grid.py
aikif/agents/gather/__init__.py
aikif/agents/gather/agent_image_metadata.py
aikif/agents/learn/__init__.py
aikif/agents/learn/dummy_learn_1.py
aikif/agents/learn/run_dummy_learn_1.py
aikif/data/CREATE_CORE_EVENTS.SQL
aikif/data/CREATE_CORE_FACTS.SQL
aikif/data/CREATE_CORE_LOCATIONS.SQL
aikif/data/CREATE_CORE_OBJECTS.SQL
aikif/data/CREATE_CORE_PEOPLE.SQL
aikif/data/CREATE_CORE_PROCESSES.SQL
aikif/data/_BUILD_ALL.SQL
aikif/data/list_agent_names.txt
aikif/data/pers_config.py
aikif/dataTools/__init__.py
aikif/dataTools/cls_data.py
aikif/dataTools/cls_data_content.py
aikif/dataTools/cls_dataset.py
aikif/dataTools/cls_datatable.py
aikif/dataTools/cls_sql_code_generator.py
aikif/dataTools/if_database.py
aikif/dataTools/if_mssqlserver.py
aikif/dataTools/if_oracle.py
aikif/dataTools/if_redis.py
aikif/data/core/EVENT_INFO-PIM-DIARY.CSV
aikif/data/core/EVENT_INFO-PIM-PROJECT.csv
aikif/data/core/EVENT_INFO-PIM-TASK.csv
aikif/data/core/EVENT_SYSTEM-PC-FILE.csv
aikif/data/core/LINK_SYSTEM-PC-FILE.csv
aikif/data/core/LOCATION_INFO-COURSE.csv
aikif/data/core/LOCATION_SYSTEM-PC-FILE.csv
aikif/data/core/LOCATION_WORLD.csv
aikif/data/core/OBJECT_INFO-COURSE.csv
aikif/data/core/OBJECT_INFO-PIM-CONTACT.csv
aikif/data/core/OBJECT_INFO-PIM-PROJECT.csv
aikif/data/core/OBJECT_OBJECT-ASSET-RESOURCE.csv
aikif/data/core/THING_INFO-PIM-SHOPPING.csv
aikif/data/core/THING_SYSTEM-PC-FILE-LECTURES.csv
aikif/data/core/projects.yaml
aikif/data/index/ndxAll.txt
aikif/data/index/ndxFull.txt
